devrev_mcp/__init__.py
devrev_mcp/server.py
devrev_mcp/utils.py
devrev_mcp-0.4.2.dist-info/METADATA
devrev_mcp-0.4.2.dist-info/WHEEL
devrev_mcp-0.4.2.dist-info/entry_points.txt
devrev_mcp-0.4.2.dist-info/licenses/LICENSE
devrev_mcp-0.4.2.dist-info/RECORD
