Metadata-Version: 2.4
Name: devrev-mcp
Version: 0.4.2
Summary: A MCP server project
Author-email: Sunil Pandey <sunil.pandey@devrev.ai>
License-File: LICENSE
Requires-Python: >=3.11
Requires-Dist: mcp>=1.0.0
Requires-Dist: requests
